res/css_light.css
res/html_template.html
res/logo.svg
res/sanitize.css
res/snail-dict-gui.desktop
snail_dict/__init__.py
snail_dict/cache.py
snail_dict/cli.py
snail_dict/conf.py
snail_dict/dict_modules/__init__.py
snail_dict/dict_modules/lexico_uk.py
snail_dict/dictionary.py
snail_dict/gui.py
snail_dict/qt.py
snail_dict/util.py
snail_dict-1.2.8.dist-info/entry_points.txt
snail_dict-1.2.8.dist-info/WHEEL
snail_dict-1.2.8.dist-info/METADATA
snail_dict-1.2.8.dist-info/RECORD
